{
  "flow_name": "childdevelopment_intro_article_tasks",
  "flow_subtype": "generated",
  "flow_type": "data_list",
  "rows": [
    {
      "id": "intro_1",
      "completed": false,
      "category_id": "intro",
      "last_in_category": true,
      "text_1": "Today's topic is about helping your child learn and grow. \n\nPlaying with your child is important for their growth and learning, both in and out of school. This is true for all children, including those with disabilities.\n\nDid you know that playing helps your child learn what is expected and how to get along with others?\n\nChildren learn a lot by asking questions. Support their interests and curiosity, and be patient when they make mistakes. We all learn from our mistakes!",
      "media_type": "audio",
      "media_title": "How will it help me and my family?",
      "media_asset": "/audio/learn_audio_1.mp3",
      "media_transcript": "Hello!\nDo you know that children learn best through playing? \n\rAnd let’s be honest, which child does not like to play? \n\rLearning takes time, but there is a lot that you can do as a parent to help your child. Let them play and explore. Let them ask questions and learn from mistakes. And be patient. Your support will help them grow and develop.",
      "attached_single_doc": "https://docs.google.com/document/d/1wUVFb8x-bFKkith4JeGM5zFS82qpNuHvmcSe1loSUwI"
    }
  ]
}