{
  "==content_list==": [
    {
      "flow_type": "template",
      "flow_name": "module_landing_selfcare",
      "status": "released",
      "parameter_list": "app_config.LAYOUT.page_padding: 0 0;",
      "comment": "selfcare",
      "comment_2": 23
    },
    {
      "flow_type": "template",
      "flow_name": "module_landing_developmentplay",
      "status": "released",
      "parameter_list": "app_config.LAYOUT.page_padding: 0 0;",
      "comment": "developmentplay",
      "comment_2": 30
    },
    {
      "flow_type": "template",
      "flow_name": "module_landing_oneononetime",
      "status": "released",
      "parameter_list": "app_config.LAYOUT.page_padding: 0 0;",
      "comment": "oneononetime",
      "comment_2": 27
    },
    {
      "flow_type": "template",
      "flow_name": "module_landing_praise",
      "status": "released",
      "parameter_list": "app_config.LAYOUT.page_padding: 0 0;",
      "comment": "praise",
      "comment_2": 21
    },
    {
      "flow_type": "template",
      "flow_name": "module_landing_feelings",
      "status": "released",
      "parameter_list": "app_config.LAYOUT.page_padding: 0 0;",
      "comment": "feelings",
      "comment_2": 23
    },
    {
      "flow_type": "template",
      "flow_name": "module_landing_instructions",
      "status": "released",
      "parameter_list": "app_config.LAYOUT.page_padding: 0 0;",
      "comment": "instructions",
      "comment_2": 27
    },
    {
      "flow_type": "template",
      "flow_name": "module_landing_rulesroutines",
      "status": "released",
      "parameter_list": "app_config.LAYOUT.page_padding: 0 0;",
      "comment": "rulesroutines",
      "comment_2": 28
    },
    {
      "flow_type": "template",
      "flow_name": "module_landing_consequences",
      "status": "released",
      "parameter_list": "app_config.LAYOUT.page_padding: 0 0;",
      "comment": "consequences",
      "comment_2": 27
    },
    {
      "flow_type": "template",
      "flow_name": "module_landing_problemsolving",
      "status": "released",
      "parameter_list": "app_config.LAYOUT.page_padding: 0 0;",
      "comment": "problemsolving",
      "comment_2": 29
    },
    {
      "flow_type": "template",
      "flow_name": "module_landing_selfcare_t",
      "status": "released",
      "parameter_list": "app_config.LAYOUT.page_padding: 0 0;",
      "comment": "selfcare_t",
      "comment_2": 25
    },
    {
      "flow_type": "template",
      "flow_name": "module_landing_oneononetime_t",
      "status": "released",
      "parameter_list": "app_config.LAYOUT.page_padding: 0 0;",
      "comment": "oneononetime_t",
      "comment_2": 29
    },
    {
      "flow_type": "template",
      "flow_name": "module_landing_praise_t",
      "status": "released",
      "parameter_list": "app_config.LAYOUT.page_padding: 0 0;",
      "comment": "praise_t",
      "comment_2": 23
    },
    {
      "flow_type": "template",
      "flow_name": "module_landing_instructions_t",
      "status": "released",
      "parameter_list": "app_config.LAYOUT.page_padding: 0 0;",
      "comment": "instructions_t",
      "comment_2": 29
    },
    {
      "flow_type": "template",
      "flow_name": "module_landing_stress_t",
      "status": "released",
      "parameter_list": "app_config.LAYOUT.page_padding: 0 0;",
      "comment": "stress_t",
      "comment_2": 23
    },
    {
      "flow_type": "template",
      "flow_name": "module_landing_problemsolving_t",
      "status": "released",
      "parameter_list": "app_config.LAYOUT.page_padding: 0 0;",
      "comment": "problemsolving_t",
      "comment_2": 31
    },
    {
      "flow_type": "template",
      "flow_name": "module_landing_money_t",
      "status": "released",
      "parameter_list": "app_config.LAYOUT.page_padding: 0 0;",
      "comment": "money_t",
      "comment_2": 22
    },
    {
      "flow_type": "template",
      "flow_name": "module_landing_rules_t",
      "status": "released",
      "parameter_list": "app_config.LAYOUT.page_padding: 0 0;",
      "comment": "rules_t",
      "comment_2": 22
    },
    {
      "flow_type": "template",
      "flow_name": "module_landing_consequences_t",
      "status": "released",
      "parameter_list": "app_config.LAYOUT.page_padding: 0 0;",
      "comment": "consequences_t",
      "comment_2": 29
    },
    {
      "flow_type": "template",
      "flow_name": "module_landing_safety_t",
      "status": "released",
      "parameter_list": "app_config.LAYOUT.page_padding: 0 0;",
      "comment": "safety_t",
      "comment_2": 23
    },
    {
      "flow_type": "template",
      "flow_name": "module_landing_crisis_t",
      "status": "released",
      "parameter_list": "app_config.LAYOUT.page_padding: 0 0;",
      "comment": "crisis_t",
      "comment_2": 23
    },
    {
      "flow_type": "template",
      "flow_name": "module_landing_celebrate_t",
      "status": "released",
      "parameter_list": "app_config.LAYOUT.page_padding: 0 0;",
      "comment": "celebrate_t",
      "comment_2": 26
    },
    {
      "flow_type": "template",
      "flow_name": "module_landing_srh_t",
      "status": "released",
      "parameter_list": "app_config.LAYOUT.page_padding: 0 0;",
      "comment": "srh_t",
      "comment_2": 20
    },
    {
      "flow_type": "template",
      "flow_name": "module_landing_stayingsafe_t",
      "status": "released",
      "parameter_list": "app_config.LAYOUT.page_padding: 0 0;",
      "comment": "stayingsafe_t",
      "comment_2": 28
    },
    {
      "flow_type": "template",
      "flow_name": "module_landing_grief_t",
      "status": "released",
      "parameter_list": "app_config.LAYOUT.page_padding: 0 0;",
      "comment": "grief_t",
      "comment_2": 22
    },
    {
      "flow_type": "template",
      "flow_name": "module_landing_learn_t",
      "status": "released",
      "parameter_list": "app_config.LAYOUT.page_padding: 0 0;",
      "comment": "learn_t",
      "comment_2": 22
    },
    {
      "flow_type": "template",
      "flow_name": "module_landing_onlinesafety_t",
      "status": "released",
      "parameter_list": "app_config.LAYOUT.page_padding: 0 0;",
      "comment": "onlinesafety_t",
      "comment_2": 29
    }
  ],
  "module_landing_selfcare": [
    {
      "type": "begin_template",
      "name": "module_landing",
      "value": "module_landing",
      "action_list": "completed | emit: completed; \nuncompleted | emit: uncompleted"
    },
    {
      "name": "module_id",
      "value": "selfcare",
      "exclude_from_translation": true
    },
    {
      "type": "end_template"
    }
  ],
  "module_landing_developmentplay": [
    {
      "type": "begin_template",
      "name": "module_landing",
      "value": "module_landing",
      "action_list": "completed | emit: completed; \nuncompleted | emit: uncompleted"
    },
    {
      "name": "module_id",
      "value": "developmentplay",
      "exclude_from_translation": true
    },
    {
      "type": "end_template"
    }
  ],
  "module_landing_oneononetime": [
    {
      "type": "begin_template",
      "name": "module_landing",
      "value": "module_landing",
      "action_list": "completed | emit: completed; \nuncompleted | emit: uncompleted"
    },
    {
      "name": "module_id",
      "value": "oneononetime",
      "exclude_from_translation": true
    },
    {
      "type": "end_template"
    }
  ],
  "module_landing_praise": [
    {
      "type": "begin_template",
      "name": "module_landing",
      "value": "module_landing",
      "action_list": "completed | emit: completed; \nuncompleted | emit: uncompleted"
    },
    {
      "name": "module_id",
      "value": "praise",
      "exclude_from_translation": true
    },
    {
      "type": "end_template"
    }
  ],
  "module_landing_feelings": [
    {
      "type": "begin_template",
      "name": "module_landing",
      "value": "module_landing",
      "action_list": "completed | emit: completed; \nuncompleted | emit: uncompleted"
    },
    {
      "name": "module_id",
      "value": "feelings",
      "exclude_from_translation": true
    },
    {
      "type": "end_template"
    }
  ],
  "module_landing_instructions": [
    {
      "type": "begin_template",
      "name": "module_landing",
      "value": "module_landing",
      "action_list": "completed | emit: completed; \nuncompleted | emit: uncompleted"
    },
    {
      "name": "module_id",
      "value": "instructions",
      "exclude_from_translation": true
    },
    {
      "type": "end_template"
    }
  ],
  "module_landing_rulesroutines": [
    {
      "type": "begin_template",
      "name": "module_landing",
      "value": "module_landing",
      "action_list": "completed | emit: completed; \nuncompleted | emit: uncompleted"
    },
    {
      "name": "module_id",
      "value": "rulesroutines",
      "exclude_from_translation": true
    },
    {
      "type": "end_template"
    }
  ],
  "module_landing_consequences": [
    {
      "type": "begin_template",
      "name": "module_landing",
      "value": "module_landing",
      "action_list": "completed | emit: completed; \nuncompleted | emit: uncompleted"
    },
    {
      "name": "module_id",
      "value": "consequences",
      "exclude_from_translation": true
    },
    {
      "type": "end_template"
    }
  ],
  "module_landing_problemsolving": [
    {
      "type": "begin_template",
      "name": "module_landing",
      "value": "module_landing",
      "action_list": "completed | emit: completed; \nuncompleted | emit: uncompleted"
    },
    {
      "name": "module_id",
      "value": "problemsolving",
      "exclude_from_translation": true
    },
    {
      "type": "end_template"
    }
  ],
  "module_landing_selfcare_t": [
    {
      "type": "begin_template",
      "name": "module_landing",
      "value": "module_landing",
      "action_list": "completed | emit: completed; \nuncompleted | emit: uncompleted"
    },
    {
      "name": "module_id",
      "value": "selfcare_t",
      "exclude_from_translation": true
    },
    {
      "type": "end_template"
    }
  ],
  "module_landing_oneononetime_t": [
    {
      "type": "begin_template",
      "name": "module_landing",
      "value": "module_landing",
      "action_list": "completed | emit: completed; \nuncompleted | emit: uncompleted"
    },
    {
      "name": "module_id",
      "value": "oneononetime_t",
      "exclude_from_translation": true
    },
    {
      "type": "end_template"
    }
  ],
  "module_landing_instructions_t": [
    {
      "type": "begin_template",
      "name": "module_landing",
      "value": "module_landing",
      "action_list": "completed | emit: completed; \nuncompleted | emit: uncompleted"
    },
    {
      "name": "module_id",
      "value": "instructions_t",
      "exclude_from_translation": true
    },
    {
      "type": "end_template"
    }
  ],
  "module_landing_praise_t": [
    {
      "type": "begin_template",
      "name": "module_landing",
      "value": "module_landing",
      "action_list": "completed | emit: completed; \nuncompleted | emit: uncompleted"
    },
    {
      "name": "module_id",
      "value": "praise_t",
      "exclude_from_translation": true
    },
    {
      "type": "end_template"
    }
  ],
  "module_landing_stress_t": [
    {
      "type": "begin_template",
      "name": "module_landing",
      "value": "module_landing",
      "action_list": "completed | emit: completed; \nuncompleted | emit: uncompleted"
    },
    {
      "name": "module_id",
      "value": "stress_t",
      "exclude_from_translation": true
    },
    {
      "type": "end_template"
    }
  ],
  "module_landing_problemsolving_t": [
    {
      "type": "begin_template",
      "name": "module_landing",
      "value": "module_landing",
      "action_list": "completed | emit: completed; \nuncompleted | emit: uncompleted"
    },
    {
      "name": "module_id",
      "value": "problemsolving_t",
      "exclude_from_translation": true
    },
    {
      "type": "end_template"
    }
  ],
  "module_landing_money_t": [
    {
      "type": "begin_template",
      "name": "module_landing",
      "value": "module_landing",
      "action_list": "completed | emit: completed; \nuncompleted | emit: uncompleted"
    },
    {
      "name": "module_id",
      "value": "money_t",
      "exclude_from_translation": true
    },
    {
      "type": "end_template"
    }
  ],
  "module_landing_rules_t": [
    {
      "type": "begin_template",
      "name": "module_landing",
      "value": "module_landing",
      "action_list": "completed | emit: completed; \nuncompleted | emit: uncompleted"
    },
    {
      "name": "module_id",
      "value": "rules_t",
      "exclude_from_translation": true
    },
    {
      "type": "end_template"
    }
  ],
  "module_landing_consequences_t": [
    {
      "type": "begin_template",
      "name": "module_landing",
      "value": "module_landing",
      "action_list": "completed | emit: completed; \nuncompleted | emit: uncompleted"
    },
    {
      "name": "module_id",
      "value": "consequences_t",
      "exclude_from_translation": true
    },
    {
      "type": "end_template"
    }
  ],
  "module_landing_safety_t": [
    {
      "type": "begin_template",
      "name": "module_landing",
      "value": "module_landing",
      "action_list": "completed | emit: completed; \nuncompleted | emit: uncompleted"
    },
    {
      "name": "module_id",
      "value": "safety_t",
      "exclude_from_translation": true
    },
    {
      "type": "end_template"
    }
  ],
  "module_landing_crisis_t": [
    {
      "type": "begin_template",
      "name": "module_landing",
      "value": "module_landing",
      "action_list": "completed | emit: completed; \nuncompleted | emit: uncompleted"
    },
    {
      "name": "module_id",
      "value": "crisis_t",
      "exclude_from_translation": true
    },
    {
      "type": "end_template"
    }
  ],
  "module_landing_celebrate_t": [
    {
      "type": "begin_template",
      "name": "module_landing",
      "value": "module_landing",
      "action_list": "completed | emit: completed; \nuncompleted | emit: uncompleted"
    },
    {
      "name": "module_id",
      "value": "celebrate_t",
      "exclude_from_translation": true
    },
    {
      "type": "end_template"
    }
  ],
  "module_landing_srh_t": [
    {
      "type": "begin_template",
      "name": "module_landing",
      "value": "module_landing",
      "action_list": "completed | emit: completed; \nuncompleted | emit: uncompleted"
    },
    {
      "name": "module_id",
      "value": "srh_t",
      "exclude_from_translation": true
    },
    {
      "type": "end_template"
    }
  ],
  "module_landing_stayingsafe_t": [
    {
      "type": "begin_template",
      "name": "module_landing",
      "value": "module_landing",
      "action_list": "completed | emit: completed; \nuncompleted | emit: uncompleted"
    },
    {
      "name": "module_id",
      "value": "stayingsafe_t",
      "exclude_from_translation": true
    },
    {
      "type": "end_template"
    }
  ],
  "module_landing_grief_t": [
    {
      "type": "begin_template",
      "name": "module_landing",
      "value": "module_landing",
      "action_list": "completed | emit: completed; \nuncompleted | emit: uncompleted"
    },
    {
      "name": "module_id",
      "value": "grief_t",
      "exclude_from_translation": true
    },
    {
      "type": "end_template"
    }
  ],
  "module_landing_learn_t": [
    {
      "type": "begin_template",
      "name": "module_landing",
      "value": "module_landing",
      "action_list": "completed | emit: completed; \nuncompleted | emit: uncompleted"
    },
    {
      "name": "module_id",
      "value": "learn_t",
      "exclude_from_translation": true
    },
    {
      "type": "end_template"
    }
  ],
  "module_landing_onlinesafety_t": [
    {
      "type": "begin_template",
      "name": "module_landing",
      "value": "module_landing",
      "action_list": "completed | emit: completed; \nuncompleted | emit: uncompleted"
    },
    {
      "name": "module_id",
      "value": "onlinesafety_t",
      "exclude_from_translation": true
    },
    {
      "type": "end_template"
    }
  ]
}