{
  "In progress versions of PLH onboarding (draft).xlsx": {
    "relativePath": "In progress versions of PLH onboarding (draft).xlsx",
    "size_kb": 246.6,
    "md5Checksum": "b52eb52a6d8741b63f058ada7d3a44a0",
    "modifiedTime": "2025-10-28T11:25:14.860Z",
    "modifiedBy": "Esmee te Winkel",
    "remoteUrl": "https://docs.google.com/spreadsheets/d/1B30-Iimf-9VApF0xLzmCm2BG6aeCdQEr6rza4c2j6Rs",
    "folderName": "1XBq4iGIZHEwzwPk3xbHDAm9WCesjR7kR"
  },
  "PLH onboarding.xlsx": {
    "relativePath": "PLH onboarding.xlsx",
    "size_kb": 238.5,
    "md5Checksum": "1e40c38f2ec686ba65fd3a1b2dbd797a",
    "modifiedTime": "2025-10-27T15:20:06.976Z",
    "modifiedBy": "Esmee te Winkel",
    "remoteUrl": "https://docs.google.com/spreadsheets/d/1LUIu_aqkzYjyUq0ecQEmWJa62CEvQ4E2L4Fkz_94ydw",
    "folderName": "1XBq4iGIZHEwzwPk3xbHDAm9WCesjR7kR"
  }
}