{
  "audio/teen/testimonials/teen/old audios_Teen test/teen_test_onlinesafety_t.mp3": {
    "overrides": {
      "theme_default": {
        "za_xh": {
          "filePath": "audio/teen/testimonials/teen/za_xh/old audios_Teen test/teen_test_onlinesafety_t.mp3",
          "md5Checksum": "b1ee12b8e38476a370da10bf0b47e85b",
          "size_kb": 240.3
        }
      }
    }
  },
  "audio/teen/testimonials/teen/old audios_Teen test/teen_test_stress_t.mp3": {
    "overrides": {
      "theme_default": {
        "za_xh": {
          "filePath": "audio/teen/testimonials/teen/za_xh/old audios_Teen test/teen_test_stress_t.mp3",
          "md5Checksum": "9ca0a93618dfa15be96028a25051a2b9",
          "size_kb": 260.1
        }
      }
    }
  }
}