{
  "==content_list==": [
    {
      "flow_type": "data_list",
      "flow_name": "language",
      "status": "released",
      "data_list_name": "language",
      "flow_subtype": "app_config_language_list"
    },
    {
      "flow_type": "data_list",
      "flow_name": "misc_global",
      "status": "released"
    }
  ],
  "language": [
    {
      "id": "gb_en",
      "country_code": "gb",
      "country_label": "United Kingdom",
      "country_icon": "images/flags/gb.svg",
      "language_code": "en",
      "language_label": "English",
      "name": "@row.id",
      "text": "@row.language_label",
      "image": "@row.country_icon",
      "comments": "Country code given by alpha-2\nhttps://en.wikipedia.org/wiki/List_of_ISO_3166_country_codes\nLanguage code given by shortest iso code\nhttps://en.wikipedia.org/wiki/List_of_ISO_639-1_codes\nShould confirm best name for country in local language, e.g.\nhttps://www.worldatlas.com/articles/names-of-countries-in-their-own-languages.html\nFlag icons added app assets, downloaded from\nhttps://flagicons.lipis.dev/"
    }
  ],
  "misc_global": [
    {
      "type": "declare_global_constant",
      "name": "yes",
      "value": "Yes"
    },
    {
      "type": "declare_global_constant",
      "name": "no",
      "value": "No"
    }
  ]
}